neuri/__init__.py
neuri/client.py
neuri/exceptions.py
neuri-1.0.1.dist-info/LICENSE.txt
neuri-1.0.1.dist-info/METADATA
neuri-1.0.1.dist-info/WHEEL
neuri-1.0.1.dist-info/top_level.txt
neuri-1.0.1.dist-info/RECORD
