Metadata-Version: 2.1
Name: neuri
Version: 1.0.1
Summary: Python client library for the Neuri API
Home-page: https://github.com/Neuri-ai/python-client
Author: Neuri
Author-email: support@neuri.ai
License: MIT License        
Keywords: api client,neuri,neuri.ai,neuri api
Classifier: Development Status :: 5 - Production/Stable
Classifier: Intended Audience :: Developers
Classifier: Topic :: Software Development :: Libraries
Classifier: License :: OSI Approved :: MIT License
Classifier: Programming Language :: Python :: 3.7
Classifier: Programming Language :: Python :: 3.8
Classifier: Programming Language :: Python :: 3.9
Classifier: Programming Language :: Python :: 3.10
Classifier: Operating System :: OS Independent
Requires-Python: >=3.7
License-File: LICENSE.txt
Requires-Dist: requests
